{
    "id": "anglo_saxons",
    "name": "Anglo Saxons",
    "units": {
        "low_bordweall": {
            "name": "Low Bordweall",
            "description": "A band of freemen, who in exchange for their lands and their freedom, serve their lord in martial service 2 months a year. As is the tradition of these people, they fight shoulder to shoulder, in the 'shield wall'.",
            "category": "infantry",
            "min": 1,
            "max": 1,
            "rules": [
                
            ],
            "keywords": [
                "Infantry"
            ],
            "models": [
                {
                    "name": "Ceorl",
                    "courage": 5,
                    "movement": 6,
                    "shoot": 5,
                    "fight": 5,
                    "defense": 6,
                    "reflexes": 5,
                    "wounds": 1,
                    "weapons": ["spear"],
                    "options": [
                        {"addRule": "shield"}
                    ],
                    "rules": ["shield"],
                    "min": 5,
                    "max": 10
            }]},
                "great_bordweall": {
                    "name": "Minor noblemen, 'wealthy peasants', and what appears to be those of the middle class, made up a class of 'retainers' who served the king and his nobles.",
                    "description": ".",
                    "category": "infantry",
                    "min": 1,
                    "max": 1,
                    "rules": [
                        
                    ],
                    "keywords": [
                        "Infantry"
                    ],
                    "models": [
                        {
                            "name": "Thegn",
                            "courage": 5,
                            "movement": 6,
                            "shoot": 5,
                            "fight": 6,
                            "defense": 6,
                            "reflexes": 6,
                            "wounds": 1,
                            "weapons": ["spear"],
                            "options": [
                                {"addRule": "shield"}
                            ],
                            "rules": ["shield"],
                            "min": 5,
                            "max": 10
                    }]}
        }
    ,
    
    "weapons": {},
    "rules": {},
    "relics": []
